espota/__init__.py
espota/__main__.py
espota-0.5.0.dist-info/METADATA
espota-0.5.0.dist-info/WHEEL
espota-0.5.0.dist-info/top_level.txt
espota-0.5.0.dist-info/RECORD
