Metadata-Version: 2.1
Name: espota
Version: 0.5.0
Summary: Cli to send firmware by ota
Home-page: UNKNOWN
Author: jadson179
Author-email: UNKNOWN
License: MIT
Platform: UNKNOWN
Classifier: Programming Language :: Python
Classifier: Programming Language :: Python :: 3.8
